jsonseq/__init__.py
jsonseq/decode.py
jsonseq/encode.py
jsonseq-1.0.0.dist-info/LICENSE
jsonseq-1.0.0.dist-info/METADATA
jsonseq-1.0.0.dist-info/WHEEL
jsonseq-1.0.0.dist-info/top_level.txt
jsonseq-1.0.0.dist-info/RECORD
