Metadata-Version: 2.1
Name: jsonseq
Version: 1.0.0
Summary: Python support for RFC 7464 JSON text sequences
Home-page: https://github.com/sgillies/jsonseq
Author: Sean Gillies
Author-email: sean.gillies@gmail.com
License: UNKNOWN
Keywords: json rfc7464
Platform: UNKNOWN
Classifier: Development Status :: 5 - Production/Stable
Classifier: Intended Audience :: Developers
Classifier: License :: OSI Approved :: MIT License
Classifier: Programming Language :: Python :: 3
Classifier: Programming Language :: Python :: 3.4
Classifier: Programming Language :: Python :: 3.5
Classifier: Programming Language :: Python :: 3.6
Classifier: Programming Language :: Python :: 3.7
Provides-Extra: dev
Provides-Extra: test
